[{"id":"6283179660010@s.whatsapp.net","balance":12},{"id":"6289688206739@s.whatsapp.net","balance":67},{"id":"6281317063255@s.whatsapp.net","balance":62},{"id":"6283110997610@s.whatsapp.net","balance":15},{"id":"6289686772774@s.whatsapp.net","balance":8},{"id":"6281276698054@s.whatsapp.net","balance":59},{"id":"16195582202@s.whatsapp.net","balance":13},{"id":"6285761413369@s.whatsapp.net","balance":4},{"id":"6289667923162@s.whatsapp.net","balance":32},{"id":"6281284210628@s.whatsapp.net","balance":18}]